cashfree_payout/__init__.py
cashfree_payout/api_client.py
cashfree_payout/api_response.py
cashfree_payout/configuration.py
cashfree_payout/exceptions.py
cashfree_payout/py.typed
cashfree_payout/rest.py
cashfree_payout/models/__init__.py
cashfree_payout/models/beneficiary.py
cashfree_payout/models/beneficiary_beneficiary_contact_details.py
cashfree_payout/models/beneficiary_beneficiary_instrument_details.py
cashfree_payout/models/create_batch_transfer_request.py
cashfree_payout/models/create_batch_transfer_request_transfers_inner.py
cashfree_payout/models/create_batch_transfer_request_transfers_inner_beneficiary_details.py
cashfree_payout/models/create_batch_transfer_request_transfers_inner_beneficiary_details_beneficiary_instrument_details.py
cashfree_payout/models/create_batch_transfer_response.py
cashfree_payout/models/create_beneficiary_request.py
cashfree_payout/models/create_beneficiary_request_beneficiary_contact_details.py
cashfree_payout/models/create_beneficiary_request_beneficiary_instrument_details.py
cashfree_payout/models/create_transfer_request.py
cashfree_payout/models/create_transfer_request_beneficiary_details.py
cashfree_payout/models/create_transfer_request_beneficiary_details_beneficiary_contact_details.py
cashfree_payout/models/create_transfer_request_beneficiary_details_beneficiary_instrument_details.py
cashfree_payout/models/create_transfer_request_beneficiary_details_beneficiary_instrument_details_card_details.py
cashfree_payout/models/create_transfer_response.py
cashfree_payout/models/create_transfer_response_beneficiary_details.py
cashfree_payout/models/create_transfer_response_beneficiary_details_beneficiary_instrument_details.py
cashfree_payout/models/error_v2.py
cashfree_payout/models/fetch_batch_transfer_response.py
cashfree_payout-0.0.13.dist-info/METADATA
cashfree_payout-0.0.13.dist-info/WHEEL
cashfree_payout-0.0.13.dist-info/top_level.txt
cashfree_payout-0.0.13.dist-info/RECORD
